<annotation><size><width>4128</width><height>3096</height><depth>3</depth></size><object><name>reference</name><bndbox><xmin>1860</xmin><ymin>415</ymin><xmax>2143</xmax><ymax>2767</ymax></bndbox><segment_polygons><polygon><point><value>1998</value><value>423</value></point><point><value>2143</value><value>415</value></point><point><value>1990</value><value>2767</value></point><point><value>1860</value><value>2754</value></point></polygon></segment_polygons></object><object><name>object</name><bndbox><xmin>869</xmin><ymin>1348</ymin><xmax>1529</xmax><ymax>2073</ymax></bndbox><segment_polygons><polygon><point><value>923</value><value>1348</value></point><point><value>1529</value><value>1385</value></point><point><value>1489</value><value>2073</value></point><point><value>869</value><value>1976</value></point></polygon></segment_polygons></object></annotation>